verilog/dff.v
module d_ff(output reg q, output qbar, input d, clk);
assign qbar = ~q;
always@(posedge clk)
q<=(d==1)?1:0;
endmodule

verilog/dff_tb.v
module dff_tb;
reg d, clk;
wire q, qbar;
d_ff dut(q, qbar,d,clk);
initial begin 
    clk = 0;
    d = 0;
end
always #2 clk = ~clk;
always #10 d = ~d;

initial begin 
    $monitor($time, "q=%b qbar=%b d=%b clk=%b", q,qbar,d,clk);
    $dumpfile("dff_tb_123.vcd");
    $dumpvars;
end
initial #100 $finish;
endmodule

verilog/dff_tb_123.vcd
$date
	Mon Nov 07 13:12:46 2022
$end
$version
	Icarus Verilog
$end
$timescale
	1s
$end
$scope module dff_tb $end
$var wire 1 ! qbar $end
$var wire 1 " q $end
$var reg 1 # clk $end
$var reg 1 $ d $end
$scope module dut $end
$var wire 1 # clk $end
$var wire 1 $ d $end
$var wire 1 ! qbar $end
$var reg 1 " q $end
$upscope $end
$upscope $end
$enddefinitions $end
#0
$dumpvars
0$
0#
x"
x!
$end
#2
1!
0"
1#
#4
0#
#6
1#
#8
0#
#10
0!
1"
1#
1$
#12
0#
#14
1#
#16
0#
#18
1#
#20
0#
0$
#22
1!
0"
1#
#24
0#
#26
1#
#28
0#
#30
0!
1"
1#
1$
#32
0#
#34
1#
#36
0#
#38
1#
#40
0#
0$
#42
1!
0"
1#
#44
0#
#46
1#
#48
0#
#50
0!
1"
1#
1$
#52
0#
#54
1#
#56
0#
#58
1#
#60
0#
0$
#62
1!
0"
1#
#64
0#
#66
1#
#68
0#
#70
0!
1"
1#
1$
#72
0#
#74
1#
#76
0#
#78
1#
#80
0#
0$
#82
1!
0"
1#
#84
0#
#86
1#
#88
0#
#90
0!
1"
1#
1$
#92
0#
#94
1#
#96
0#
#98
1#
#100
0#
0$
