verilog/mfGate_gatelevel.v
module mfGate(input x,y, a,b,
              output f);
    
    wire w0, w1, w2, w3;

    /* Using an all-NAND implementation,
    for faster critical path delay and minimum area (in terms of MOSFETs).*/
    nand(w0,  x, ~a, ~b);
    nand(w1, ~x,  a,  b);
    nand(w2,  y, ~a,  b); // We could have used a XOR gate for a'b + ab'
    nand(w3,  y,  a, ~b); // , but it is inefficient in both speed and area.

    nand(f, w0, w1, w2, w3);

endmodule

verilog/.v
`timescale 1ns/1ps

module tb_mfGate();
    reg tb_x,tb_y, tb_a,tb_b;
    wire tb_f;
    mfGate mfg (.x(tb_x),.y(tb_y) , .a(tb_a),.b(tb_b) , .f(tb_f));
    integer i;
    initial begin
        i = 0;
        {tb_x,tb_y , tb_a,tb_b} = {i}; i=1+1; // To avoid the 4'bxxxx at the beginning.
        for(i = 0 ; i<16; i=i+1 ) begin
            #1 {tb_x,tb_y , tb_a,tb_b} = {i};
        end
    end
    initial begin
        $monitor("time = %0d , {x,y , a,b} = {%b,%b , %b,%b} , f = %b", $time, tb_x,tb_y , tb_a,tb_b, tb_f);
        $dumpfile("./dump.vcd");
        $dumpvars();
    end
endmodule

verilog/dump.vcd
$date
	Fri Nov 04 07:17:17 2022
$end
$version
	Icarus Verilog
$end
$timescale
	1ps
$end
$scope module tb_mfGate $end
$var wire 1 ! tb_f $end
$var reg 1 " tb_a $end
$var reg 1 # tb_b $end
$var reg 1 $ tb_x $end
$var reg 1 % tb_y $end
$var integer 32 & i [31:0] $end
$scope module mfg $end
$var wire 1 " a $end
$var wire 1 # b $end
$var wire 1 ! f $end
$var wire 1 ' w0 $end
$var wire 1 ( w1 $end
$var wire 1 ) w2 $end
$var wire 1 * w3 $end
$var wire 1 $ x $end
$var wire 1 % y $end
$upscope $end
$upscope $end
$enddefinitions $end
#0
$dumpvars
1*
1)
1(
1'
b0 &
0%
0$
0#
0"
0!
$end
#1000
b1 &
#2000
b10 &
1#
#3000
b11 &
1"
0#
#4000
1!
0(
b100 &
1#
#5000
0!
1(
b101 &
1%
0"
0#
#6000
1!
0)
b110 &
1#
#7000
0*
1)
b111 &
1"
0#
#8000
1*
0(
b1000 &
1#
#9000
0'
1(
b1001 &
1$
0%
0"
0#
#10000
0!
1'
b1010 &
1#
#11000
b1011 &
1"
0#
#12000
b1100 &
1#
#13000
1!
0'
b1101 &
1%
0"
0#
#14000
1'
0)
b1110 &
1#
#15000
0*
1)
b1111 &
1"
0#
#16000
0!
1*
b10000 &
1#
