verilog/jk_ff.v
module jk_ff(output reg q, output qbar, input j,k,clk,rst);
assign qbar = ~q;
always@(posedge clk)
begin 
    if(!rst)
    case({j,k})
    2'b00: q <= q; 
    2'b01: q <= 0; 
    2'b10: q <= 1;
    2'b11: q <= ~q; 
    endcase
end
endmodule

verilog/jk_ff_tb.v
module jkff_tb;
wire q,qbar;
reg j,k,clk,rst;
jk_ff dut(q,qbar,j,k,clk,rst);

initial begin
    clk = 0; j=0; k=0;
    rst=1;
    #10 rst=0;
end

always #4 clk = ~clk;
always #6 j = ~j;
always #8 k = ~k;
initial begin 
    $monitor("clk=%b j=%b k=%b q=%b qbar=%b", clk, j, k, q, qbar);
    $dumpfile("jk_fipflop.vcd");
    $dumpvars;
    #100 $finish;
end
endmodule

verilog/jk_fipflop.vcd
$date
	Mon Nov 07 13:21:48 2022
$end
$version
	Icarus Verilog
$end
$timescale
	1s
$end
$scope module jkff_tb $end
$var wire 1 ! qbar $end
$var wire 1 " q $end
$var reg 1 # clk $end
$var reg 1 $ j $end
$var reg 1 % k $end
$var reg 1 & rst $end
$scope module dut $end
$var wire 1 # clk $end
$var wire 1 $ j $end
$var wire 1 % k $end
$var wire 1 ! qbar $end
$var wire 1 & rst $end
$var reg 1 " q $end
$upscope $end
$upscope $end
$enddefinitions $end
#0
$dumpvars
1&
0%
0$
0#
x"
x!
$end
#4
1#
#6
1$
#8
0#
1%
#10
0&
#12
1!
0"
1#
0$
#16
0#
0%
#18
1$
#20
0!
1"
1#
#24
0#
0$
1%
#28
1!
0"
1#
#30
1$
#32
0#
0%
#36
1#
0$
#40
0#
1%
#42
1$
#44
0!
1"
1#
#48
0#
0$
0%
#52
1#
#54
1$
#56
0#
1%
#60
1!
0"
1#
0$
#64
0#
0%
#66
1$
#68
0!
1"
1#
#72
0#
0$
1%
#76
1!
0"
1#
#78
1$
#80
0#
0%
#84
1#
0$
#88
0#
1%
#90
1$
#92
0!
1"
1#
#96
0#
0$
0%
