verilog/q1_mfg_1.v
module q1_mfg_1(f,a,b,x,y);
output f;
input a,b,x,y;
reg f;
always @(a or b or x or y)
case({x,y})
   2'b00:f=a&b;
   2'b01:f=a|b;
   2'b10:f=~(a|b);
   2'b11:f=~(a&b);
endcase
endmodule

verilog/q1_mfg_tb.v
module q1_mfg_tb;
reg a,b,x,y;
wire f;
q1_mfg_1 m(f,a,b,x,y);

initial begin
    a=0;b=0;x=0;y=0;
    #32 $finish;
end
always #2 y=~y;
always #4 x=~x;
always #8 b=~b;
always #16 a=~a;

initial begin
    $display("x,y=00 is AND \nx,y=01 is OR \nx,y=10 is NOR \nx,y=11 is NAND");
    $monitor($time, "x,y=%b%b a=%b b=%b y=%b",x,y,a,b,f);
    $dumpfile("mfgwave.vcd");
    $dumpvars;
end
endmodule

verilog/mfgwave.vcd
$date
	Fri Nov 04 16:40:35 2022
$end
$version
	Icarus Verilog
$end
$timescale
	1s
$end
$scope module q1_mfg_tb $end
$var wire 1 ! f $end
$var reg 1 " a $end
$var reg 1 # b $end
$var reg 1 $ x $end
$var reg 1 % y $end
$scope module m $end
$var wire 1 " a $end
$var wire 1 # b $end
$var wire 1 $ x $end
$var wire 1 % y $end
$var reg 1 ! f $end
$upscope $end
$upscope $end
$enddefinitions $end
#0
$dumpvars
0%
0$
0#
0"
0!
$end
#2
1%
#4
1!
0%
1$
#6
1%
#8
0!
0%
0$
1#
#10
1!
1%
#12
0!
0%
1$
#14
1!
1%
#16
0!
0%
0$
0#
1"
#18
1!
1%
#20
0!
0%
1$
#22
1!
1%
#24
0%
0$
1#
#26
1%
#28
0!
0%
1$
#30
1%
#32
0%
0$
0#
0"
