verilog/q2.v
module mux2to1(y,a,b,s);
output y;
input a,b,s;
wire sbar,s_a,s_b;
not(sbar,s);
and(s_a,sbar,a);
and(s_b,s,b);
or(y,s_b,s_a);
endmodule

module mux8to1(y,d,s);
output y;
input [7:0]d;
input [2:0]s;
wire w1,w2,w3,w4,w5,w6;
mux2to1 m1(w1,d[0],d[1],s[0]);
mux2to1 m2(w2,d[2],d[3],s[0]);
mux2to1 m3(w3,d[4],d[5],s[0]);
mux2to1 m4(w4,d[6],d[7],s[0]);
mux2to1 m5(w5,w1,w2,s[1]);
mux2to1 m6(w6,w3,w4,s[1]);
mux2to1 m7(y,w5,w6,s[2]);
endmodule

verilog/q2_tb.v
module mux_tb;
reg [7:0]d;
reg [2:0]s;
wire y;
mux8to1 mut(.y(y),.d(d),.s(s));
initial begin
  d=8'b10110110;
  #2 s=3'b000;
  #2 s=3'b001;
  #2 s=3'b010;
  #2 s=3'b011;
  #2 s=3'b100;
  #2 s=3'b101;
  #2 s=3'b110;
  #2 s=3'b111;
end

initial begin
  $monitor("time=%g,y=%b s=%b d=%b",$time,y,s,d);
  $dumpfile("muxwave.vcd");
  $dumpvars();
end
endmodule

verilog/muxwave.vcd
$date
	Fri Nov 04 16:13:00 2022
$end
$version
	Icarus Verilog
$end
$timescale
	1s
$end
$scope module mux_tb $end
$var wire 1 ! y $end
$var reg 8 " d [7:0] $end
$var reg 3 # s [2:0] $end
$scope module mut $end
$var wire 8 $ d [7:0] $end
$var wire 3 % s [2:0] $end
$var wire 1 ! y $end
$var wire 1 & w6 $end
$var wire 1 ' w5 $end
$var wire 1 ( w4 $end
$var wire 1 ) w3 $end
$var wire 1 * w2 $end
$var wire 1 + w1 $end
$scope module m1 $end
$var wire 1 , a $end
$var wire 1 - b $end
$var wire 1 . s $end
$var wire 1 / s_a $end
$var wire 1 0 s_b $end
$var wire 1 1 sbar $end
$var wire 1 + y $end
$upscope $end
$scope module m2 $end
$var wire 1 2 a $end
$var wire 1 3 b $end
$var wire 1 4 s $end
$var wire 1 5 s_a $end
$var wire 1 6 s_b $end
$var wire 1 7 sbar $end
$var wire 1 * y $end
$upscope $end
$scope module m3 $end
$var wire 1 8 a $end
$var wire 1 9 b $end
$var wire 1 : s $end
$var wire 1 ; s_a $end
$var wire 1 < s_b $end
$var wire 1 = sbar $end
$var wire 1 ) y $end
$upscope $end
$scope module m4 $end
$var wire 1 > a $end
$var wire 1 ? b $end
$var wire 1 @ s $end
$var wire 1 A s_a $end
$var wire 1 B s_b $end
$var wire 1 C sbar $end
$var wire 1 ( y $end
$upscope $end
$scope module m5 $end
$var wire 1 + a $end
$var wire 1 * b $end
$var wire 1 D s $end
$var wire 1 E s_a $end
$var wire 1 F s_b $end
$var wire 1 G sbar $end
$var wire 1 ' y $end
$upscope $end
$scope module m6 $end
$var wire 1 ) a $end
$var wire 1 ( b $end
$var wire 1 H s $end
$var wire 1 I s_a $end
$var wire 1 J s_b $end
$var wire 1 K sbar $end
$var wire 1 & y $end
$upscope $end
$scope module m7 $end
$var wire 1 ' a $end
$var wire 1 & b $end
$var wire 1 L s $end
$var wire 1 M s_a $end
$var wire 1 N s_b $end
$var wire 1 O sbar $end
$var wire 1 ! y $end
$upscope $end
$upscope $end
$upscope $end
$enddefinitions $end
#0
$dumpvars
xO
xN
xM
xL
xK
xJ
xI
xH
xG
xF
xE
xD
xC
xB
0A
x@
1?
0>
x=
x<
x;
x:
19
18
x7
06
x5
x4
03
12
x1
x0
0/
x.
1-
0,
x+
x*
x)
x(
x'
x&
bx %
b10110110 $
bx #
b10110110 "
x!
$end
#2
0!
0M
1&
0'
1I
0E
1*
1)
0+
15
1;
0(
11
00
17
1=
0<
1C
0B
1G
0F
1K
0J
1O
0N
0.
04
0:
0@
0D
0H
0L
b0 #
b0 %
#4
1!
1M
1'
1E
0*
1+
05
0;
1(
01
10
07
0=
1<
0C
1B
1.
14
1:
1@
b1 #
b1 %
#6
1!
1F
0&
1M
1*
1'
0+
15
1;
1)
0(
0E
0I
11
00
17
1=
0<
1C
0B
0G
0K
0J
0.
04
0:
0@
1D
1H
b10 #
b10 %
#8
0!
0M
0'
0F
1&
0*
1J
1+
05
0;
1(
01
10
07
0=
1<
0C
1B
1.
14
1:
1@
b11 #
b11 %
#10
1*
0'
0+
15
1;
1)
0(
0E
1I
1&
1!
11
00
17
1=
0<
1C
0B
1G
1K
0J
0O
1N
0.
04
0:
0@
0D
0H
1L
b100 #
b100 %
#12
1'
1E
0*
1+
05
0;
1(
01
10
07
0=
1<
0C
1B
1.
14
1:
1@
b101 #
b101 %
#14
0!
0N
1F
0&
1*
1'
0+
15
1;
1)
0(
0E
0I
11
00
17
1=
0<
1C
0B
0G
0K
0J
0.
04
0:
0@
1D
1H
b110 #
b110 %
#16
1!
0'
1N
0F
1&
0*
1J
1+
05
0;
1(
01
10
07
0=
1<
0C
1B
1.
14
1:
1@
b111 #
b111 %
